flask_composer
