Metadata-Version: 1.1
Name: Flask-Composer
Version: 0.3.2
Summary: Composite Web UI extension for Flask
Home-page: https://github.com/denis-itskovich/flask-composer
Author: Denis Itskovich
Author-email: denis.itskovich@gmail.com
License: Apache 2.0
Keywords: flask,composite,web,flask-composer
Platform: UNKNOWN
Classifier: Development Status :: 2 - Pre-Alpha
Classifier: Programming Language :: Python
Classifier: Programming Language :: Python :: 2.6
Classifier: Programming Language :: Python :: 2.7
Classifier: Programming Language :: Python :: 3.3
Classifier: Programming Language :: Python :: 3.4
Classifier: Environment :: Web Environment
Classifier: Framework :: Flask
Classifier: License :: OSI Approved :: Apache Software License
